[
    {
        "model": "movie_app.serial",
        "pk": 1,
        "fields": {
            "name": "Задача трех тел",
            "rating": 7.0,
            "rating_imdb": 7.0,
            "year": 2024,
            "budget": 13984,
            "description": "В 1967 году девушка-астрофизик — классовый враг и дочь насмерть забитого хунвэйбинами профессора — начинает работать в сверхсекретной лаборатории во Внутренней Монголии, где пытаются отправлять сигналы возможным внеземным цивилизациям.\r\n\r\n2024 год. Ускорители частиц по всему миру показывают результаты, которые опровергают известные законы физики, а также происходит серия загадочных самоубийств учёных.",
            "slug": "zadacha-treh-tel",
            "currency": "USD",
            "director": null,
            "category_serial": "NEWRELEASES",
            "age": 18,
            "time": 60.0,
            "image": "serials/3_Body_Problem_Netflix_poster.jpg",
            "image_back": "serial_back/Снимок_экрана_2024-05-30_164250.png",
            "actors": [
                1,
                2
            ]
        }
    },
    {
        "model": "movie_app.serial",
        "pk": 2,
        "fields": {
            "name": "Губка боб",
            "rating": 10.0,
            "rating_imdb": 10.0,
            "year": 1999,
            "budget": 10,
            "description": "Население подводного городка Бикини Боттом составляют разные морские обитатели. Среди них — лучший друг Спанч Боба, морская звезда по имени Патрик, раздражительный надменный кальмар Сквидвард и белка по имени Сэнди, которая тоже живёт под водой, используя гидрокостюм. Спанч Боб работает поваром в закусочной «Красти Краб», которая управляется старым скрягой мистером Крабсом",
            "slug": "gubka-bob",
            "currency": "RUB",
            "director": null,
            "category_serial": "CLASSICS",
            "age": 12,
            "time": 0.22,
            "image": "serials/300x450_3.webp",
            "image_back": "serial_back/Без_названия_6.jpeg",
            "actors": [
                1
            ]
        }
    }
]
